immogpt/__init__.py
immogpt/cli.py
immogpt/immogpt.py
immogpt-0.1.0.dist-info/AUTHORS.rst
immogpt-0.1.0.dist-info/METADATA
immogpt-0.1.0.dist-info/WHEEL
immogpt-0.1.0.dist-info/entry_points.txt
immogpt-0.1.0.dist-info/top_level.txt
immogpt-0.1.0.dist-info/RECORD
