Metadata-Version: 2.1
Name: immogpt
Version: 0.1.0
Summary: An apartment Search engine
Home-page: https://github.com/wuqunfei/immogpt
Author: Qunfei Wu
Author-email: wu.qunfei@gmail.com
Keywords: immogpt
Classifier: Development Status :: 2 - Pre-Alpha
Classifier: Intended Audience :: Developers
Classifier: Natural Language :: English
Classifier: Programming Language :: Python :: 3
Classifier: Programming Language :: Python :: 3.10
Requires-Python: >=3.6
License-File: AUTHORS.rst
